schocken/__init__.py
schocken/__main__.py
schocken/bot.py
schocken/deckel_management.py
schocken/events.py
schocken/exceptions.py
schocken/spiel.py
schocken/spieler.py
schocken/wuerfel.py
schocken/wurf.py
schocken-0.2.0.dist-info/METADATA
schocken-0.2.0.dist-info/WHEEL
schocken-0.2.0.dist-info/entry_points.txt
schocken-0.2.0.dist-info/top_level.txt
schocken-0.2.0.dist-info/RECORD
